oksana/__init__.py
professor_oksana-1.0.0.dist-info/METADATA
professor_oksana-1.0.0.dist-info/WHEEL
professor_oksana-1.0.0.dist-info/top_level.txt
professor_oksana-1.0.0.dist-info/RECORD
