Metadata-Version: 2.1
Name: professor-oksana
Version: 1.0.0
Summary: Imports oksana
Author: Jean Eckelberg
License: MIT
Requires-Dist: tqdm >=4.66.1
